{
  "code": 200,
  "status": "OK",
  "data": {
    "number": 515,
    "ayahs": [
      {
        "number": 4612,
        "text": "Muhammad est le Messager d'Allah. Et ceux qui sont avec lui sont durs envers les mécréants, miséricordieux entre eux. Tu les vois inclinés, prosternés, recherchant d'Allah grâce et agrément. Leurs visages sont marqués par la trace laissée par la prosternation. Telle est leur image dans la Thora. Et l'image que l'on donne d'eux dans l'Evangile est celle d'une semence qui sort sa pousse, puis se raffermit, s'épaissit, et ensuite se dresse sur sa tige, à l'émerveillement des semeurs. [Allah] par eux [les croyants] remplit de dépit les mécréants. Allah promet à ceux d'entre eux qui croient et font de bonnes œuvres, un pardon et une énorme récompense.",
        "surah": {
          "number": 48,
          "name": "سُورَةُ الفَتۡحِ",
          "englishName": "Al-Fath",
          "englishNameTranslation": "The Victory",
          "revelationType": "Medinan",
          "numberOfAyahs": 29
        },
        "numberInSurah": 29,
        "juz": 26,
        "manzil": 6,
        "page": 515,
        "ruku": 449,
        "hizbQuarter": 205,
        "sajda": false
      },
      {
        "number": 4613,
        "text": "O vous qui avez cru! Ne devancez pas Allah et Son messager. Et craignez Allah. Allah est Audient et Omniscient.",
        "surah": {
          "number": 49,
          "name": "سُورَةُ الحُجُرَاتِ",
          "englishName": "Al-Hujuraat",
          "englishNameTranslation": "The Inner Apartments",
          "revelationType": "Medinan",
          "numberOfAyahs": 18
        },
        "numberInSurah": 1,
        "juz": 26,
        "manzil": 6,
        "page": 515,
        "ruku": 450,
        "hizbQuarter": 206,
        "sajda": false
      },
      {
        "number": 4614,
        "text": "O vous qui avez cru! N'élevez pas vos voix au-dessus de la voix du Prophète, et ne haussez pas le ton en lui parlant, comme vous le haussez les uns avec les autres, sinon vos œuvres deviendraient vaines sans que vous vous en rendiez compte.",
        "surah": {
          "number": 49,
          "name": "سُورَةُ الحُجُرَاتِ",
          "englishName": "Al-Hujuraat",
          "englishNameTranslation": "The Inner Apartments",
          "revelationType": "Medinan",
          "numberOfAyahs": 18
        },
        "numberInSurah": 2,
        "juz": 26,
        "manzil": 6,
        "page": 515,
        "ruku": 450,
        "hizbQuarter": 206,
        "sajda": false
      },
      {
        "number": 4615,
        "text": "Ceux qui auprès du Messager d'Allah baissent leurs voix sont ceux dont Allah a éprouvé les cœurs pour la piété. Ils auront un pardon et une énorme récompense.",
        "surah": {
          "number": 49,
          "name": "سُورَةُ الحُجُرَاتِ",
          "englishName": "Al-Hujuraat",
          "englishNameTranslation": "The Inner Apartments",
          "revelationType": "Medinan",
          "numberOfAyahs": 18
        },
        "numberInSurah": 3,
        "juz": 26,
        "manzil": 6,
        "page": 515,
        "ruku": 450,
        "hizbQuarter": 206,
        "sajda": false
      },
      {
        "number": 4616,
        "text": "Ceux qui t'appellent à haute voix de derrière les appartements, la plupart d'entre eux ne raisonnent pas.",
        "surah": {
          "number": 49,
          "name": "سُورَةُ الحُجُرَاتِ",
          "englishName": "Al-Hujuraat",
          "englishNameTranslation": "The Inner Apartments",
          "revelationType": "Medinan",
          "numberOfAyahs": 18
        },
        "numberInSurah": 4,
        "juz": 26,
        "manzil": 6,
        "page": 515,
        "ruku": 450,
        "hizbQuarter": 206,
        "sajda": false
      }
    ],
    "surahs": {
      "48": {
        "number": 48,
        "name": "سُورَةُ الفَتۡحِ",
        "englishName": "Al-Fath",
        "englishNameTranslation": "The Victory",
        "revelationType": "Medinan",
        "numberOfAyahs": 29
      },
      "49": {
        "number": 49,
        "name": "سُورَةُ الحُجُرَاتِ",
        "englishName": "Al-Hujuraat",
        "englishNameTranslation": "The Inner Apartments",
        "revelationType": "Medinan",
        "numberOfAyahs": 18
      }
    },
    "edition": {
      "identifier": "fr.hamidullah",
      "language": "fr",
      "name": "Hamidullah",
      "englishName": "Muhammad Hamidullah",
      "format": "text",
      "type": "translation",
      "direction": "ltr"
    }
  }
}