{
  "code": 200,
  "status": "OK",
  "data": {
    "number": 522,
    "ayahs": [
      {
        "number": 4706,
        "text": "Alors [Abraham] dit: «Quelle est donc votre mission, ô envoyés?»",
        "surah": {
          "number": 51,
          "name": "سُورَةُ الذَّارِيَاتِ",
          "englishName": "Adh-Dhaariyat",
          "englishNameTranslation": "The Winnowing Winds",
          "revelationType": "Meccan",
          "numberOfAyahs": 60
        },
        "numberInSurah": 31,
        "juz": 27,
        "manzil": 7,
        "page": 522,
        "ruku": 456,
        "hizbQuarter": 209,
        "sajda": false
      },
      {
        "number": 4707,
        "text": "Ils dirent: «Nous avons été envoyés vers des gens criminels,",
        "surah": {
          "number": 51,
          "name": "سُورَةُ الذَّارِيَاتِ",
          "englishName": "Adh-Dhaariyat",
          "englishNameTranslation": "The Winnowing Winds",
          "revelationType": "Meccan",
          "numberOfAyahs": 60
        },
        "numberInSurah": 32,
        "juz": 27,
        "manzil": 7,
        "page": 522,
        "ruku": 456,
        "hizbQuarter": 209,
        "sajda": false
      },
      {
        "number": 4708,
        "text": "pour lancer sur eux des pierres de glaise,",
        "surah": {
          "number": 51,
          "name": "سُورَةُ الذَّارِيَاتِ",
          "englishName": "Adh-Dhaariyat",
          "englishNameTranslation": "The Winnowing Winds",
          "revelationType": "Meccan",
          "numberOfAyahs": 60
        },
        "numberInSurah": 33,
        "juz": 27,
        "manzil": 7,
        "page": 522,
        "ruku": 456,
        "hizbQuarter": 209,
        "sajda": false
      },
      {
        "number": 4709,
        "text": "marquées auprès de ton Seigneur à l'intention des outranciers».",
        "surah": {
          "number": 51,
          "name": "سُورَةُ الذَّارِيَاتِ",
          "englishName": "Adh-Dhaariyat",
          "englishNameTranslation": "The Winnowing Winds",
          "revelationType": "Meccan",
          "numberOfAyahs": 60
        },
        "numberInSurah": 34,
        "juz": 27,
        "manzil": 7,
        "page": 522,
        "ruku": 456,
        "hizbQuarter": 209,
        "sajda": false
      },
      {
        "number": 4710,
        "text": "Nous en fîmes sortir alors ce qu'il y avait comme croyants,",
        "surah": {
          "number": 51,
          "name": "سُورَةُ الذَّارِيَاتِ",
          "englishName": "Adh-Dhaariyat",
          "englishNameTranslation": "The Winnowing Winds",
          "revelationType": "Meccan",
          "numberOfAyahs": 60
        },
        "numberInSurah": 35,
        "juz": 27,
        "manzil": 7,
        "page": 522,
        "ruku": 456,
        "hizbQuarter": 209,
        "sajda": false
      },
      {
        "number": 4711,
        "text": "mais Nous n'y trouvâmes qu'une seule maison de gens soumis.",
        "surah": {
          "number": 51,
          "name": "سُورَةُ الذَّارِيَاتِ",
          "englishName": "Adh-Dhaariyat",
          "englishNameTranslation": "The Winnowing Winds",
          "revelationType": "Meccan",
          "numberOfAyahs": 60
        },
        "numberInSurah": 36,
        "juz": 27,
        "manzil": 7,
        "page": 522,
        "ruku": 456,
        "hizbQuarter": 209,
        "sajda": false
      },
      {
        "number": 4712,
        "text": "Et Nous y laissâmes un signe pour ceux qui redoutent le douloureux châtiment;",
        "surah": {
          "number": 51,
          "name": "سُورَةُ الذَّارِيَاتِ",
          "englishName": "Adh-Dhaariyat",
          "englishNameTranslation": "The Winnowing Winds",
          "revelationType": "Meccan",
          "numberOfAyahs": 60
        },
        "numberInSurah": 37,
        "juz": 27,
        "manzil": 7,
        "page": 522,
        "ruku": 456,
        "hizbQuarter": 209,
        "sajda": false
      },
      {
        "number": 4713,
        "text": "[Il y a même un signe] en Moïse quand Nous l'envoyâmes, avec une preuve évidente, vers Pharaon.",
        "surah": {
          "number": 51,
          "name": "سُورَةُ الذَّارِيَاتِ",
          "englishName": "Adh-Dhaariyat",
          "englishNameTranslation": "The Winnowing Winds",
          "revelationType": "Meccan",
          "numberOfAyahs": 60
        },
        "numberInSurah": 38,
        "juz": 27,
        "manzil": 7,
        "page": 522,
        "ruku": 456,
        "hizbQuarter": 209,
        "sajda": false
      },
      {
        "number": 4714,
        "text": "Mais [celui-ci] se détourna confiant en sa puissance, et dit: «C'est un magicien ou un possédé!»",
        "surah": {
          "number": 51,
          "name": "سُورَةُ الذَّارِيَاتِ",
          "englishName": "Adh-Dhaariyat",
          "englishNameTranslation": "The Winnowing Winds",
          "revelationType": "Meccan",
          "numberOfAyahs": 60
        },
        "numberInSurah": 39,
        "juz": 27,
        "manzil": 7,
        "page": 522,
        "ruku": 456,
        "hizbQuarter": 209,
        "sajda": false
      },
      {
        "number": 4715,
        "text": "Nous le saisîmes ainsi que ses troupes, puis les jetâmes dans les flots, pour son comportement blâmable.",
        "surah": {
          "number": 51,
          "name": "سُورَةُ الذَّارِيَاتِ",
          "englishName": "Adh-Dhaariyat",
          "englishNameTranslation": "The Winnowing Winds",
          "revelationType": "Meccan",
          "numberOfAyahs": 60
        },
        "numberInSurah": 40,
        "juz": 27,
        "manzil": 7,
        "page": 522,
        "ruku": 456,
        "hizbQuarter": 209,
        "sajda": false
      },
      {
        "number": 4716,
        "text": "De même pour les 'Aad, quand Nous envoyâmes contre eux le vent dévastateur",
        "surah": {
          "number": 51,
          "name": "سُورَةُ الذَّارِيَاتِ",
          "englishName": "Adh-Dhaariyat",
          "englishNameTranslation": "The Winnowing Winds",
          "revelationType": "Meccan",
          "numberOfAyahs": 60
        },
        "numberInSurah": 41,
        "juz": 27,
        "manzil": 7,
        "page": 522,
        "ruku": 456,
        "hizbQuarter": 209,
        "sajda": false
      },
      {
        "number": 4717,
        "text": "n'épargnant rien sur son passage sans le réduire en poussière.",
        "surah": {
          "number": 51,
          "name": "سُورَةُ الذَّارِيَاتِ",
          "englishName": "Adh-Dhaariyat",
          "englishNameTranslation": "The Winnowing Winds",
          "revelationType": "Meccan",
          "numberOfAyahs": 60
        },
        "numberInSurah": 42,
        "juz": 27,
        "manzil": 7,
        "page": 522,
        "ruku": 456,
        "hizbQuarter": 209,
        "sajda": false
      },
      {
        "number": 4718,
        "text": "De même pour les Thamûd, quand il leur fut dit: «Jouissez jusqu'à un certain temps!»",
        "surah": {
          "number": 51,
          "name": "سُورَةُ الذَّارِيَاتِ",
          "englishName": "Adh-Dhaariyat",
          "englishNameTranslation": "The Winnowing Winds",
          "revelationType": "Meccan",
          "numberOfAyahs": 60
        },
        "numberInSurah": 43,
        "juz": 27,
        "manzil": 7,
        "page": 522,
        "ruku": 456,
        "hizbQuarter": 209,
        "sajda": false
      },
      {
        "number": 4719,
        "text": "Ils défièrent le commandement de leur Seigneur. La foudre les saisit alors qu'ils regardaient.",
        "surah": {
          "number": 51,
          "name": "سُورَةُ الذَّارِيَاتِ",
          "englishName": "Adh-Dhaariyat",
          "englishNameTranslation": "The Winnowing Winds",
          "revelationType": "Meccan",
          "numberOfAyahs": 60
        },
        "numberInSurah": 44,
        "juz": 27,
        "manzil": 7,
        "page": 522,
        "ruku": 456,
        "hizbQuarter": 209,
        "sajda": false
      },
      {
        "number": 4720,
        "text": "Ils ne purent ni se mettre debout ni être secourus.",
        "surah": {
          "number": 51,
          "name": "سُورَةُ الذَّارِيَاتِ",
          "englishName": "Adh-Dhaariyat",
          "englishNameTranslation": "The Winnowing Winds",
          "revelationType": "Meccan",
          "numberOfAyahs": 60
        },
        "numberInSurah": 45,
        "juz": 27,
        "manzil": 7,
        "page": 522,
        "ruku": 456,
        "hizbQuarter": 209,
        "sajda": false
      },
      {
        "number": 4721,
        "text": "De même, pour le peuple de Noé auparavant. Ils étaient des gens pervers.",
        "surah": {
          "number": 51,
          "name": "سُورَةُ الذَّارِيَاتِ",
          "englishName": "Adh-Dhaariyat",
          "englishNameTranslation": "The Winnowing Winds",
          "revelationType": "Meccan",
          "numberOfAyahs": 60
        },
        "numberInSurah": 46,
        "juz": 27,
        "manzil": 7,
        "page": 522,
        "ruku": 456,
        "hizbQuarter": 209,
        "sajda": false
      },
      {
        "number": 4722,
        "text": "Le ciel, Nous l'avons construit par Notre puissance: et Nous l'étendons [constamment] dans l'immensité.",
        "surah": {
          "number": 51,
          "name": "سُورَةُ الذَّارِيَاتِ",
          "englishName": "Adh-Dhaariyat",
          "englishNameTranslation": "The Winnowing Winds",
          "revelationType": "Meccan",
          "numberOfAyahs": 60
        },
        "numberInSurah": 47,
        "juz": 27,
        "manzil": 7,
        "page": 522,
        "ruku": 457,
        "hizbQuarter": 209,
        "sajda": false
      },
      {
        "number": 4723,
        "text": "Et la terre, Nous l'avons étendue. Et de quelle excellente façon Nous l'avons nivelée!",
        "surah": {
          "number": 51,
          "name": "سُورَةُ الذَّارِيَاتِ",
          "englishName": "Adh-Dhaariyat",
          "englishNameTranslation": "The Winnowing Winds",
          "revelationType": "Meccan",
          "numberOfAyahs": 60
        },
        "numberInSurah": 48,
        "juz": 27,
        "manzil": 7,
        "page": 522,
        "ruku": 457,
        "hizbQuarter": 209,
        "sajda": false
      },
      {
        "number": 4724,
        "text": "Et de toute chose Nous avons créé [deux éléments] de couple. Peut-être vous rappellerez-vous?",
        "surah": {
          "number": 51,
          "name": "سُورَةُ الذَّارِيَاتِ",
          "englishName": "Adh-Dhaariyat",
          "englishNameTranslation": "The Winnowing Winds",
          "revelationType": "Meccan",
          "numberOfAyahs": 60
        },
        "numberInSurah": 49,
        "juz": 27,
        "manzil": 7,
        "page": 522,
        "ruku": 457,
        "hizbQuarter": 209,
        "sajda": false
      },
      {
        "number": 4725,
        "text": "«Fuyez donc vers Allah. Moi, je suis pour vous de Sa part, un avertisseur explicite.",
        "surah": {
          "number": 51,
          "name": "سُورَةُ الذَّارِيَاتِ",
          "englishName": "Adh-Dhaariyat",
          "englishNameTranslation": "The Winnowing Winds",
          "revelationType": "Meccan",
          "numberOfAyahs": 60
        },
        "numberInSurah": 50,
        "juz": 27,
        "manzil": 7,
        "page": 522,
        "ruku": 457,
        "hizbQuarter": 209,
        "sajda": false
      },
      {
        "number": 4726,
        "text": "Ne placez pas avec Allah une autre divinité. Je suis pour vous de Sa part, un avertisseur explicite».",
        "surah": {
          "number": 51,
          "name": "سُورَةُ الذَّارِيَاتِ",
          "englishName": "Adh-Dhaariyat",
          "englishNameTranslation": "The Winnowing Winds",
          "revelationType": "Meccan",
          "numberOfAyahs": 60
        },
        "numberInSurah": 51,
        "juz": 27,
        "manzil": 7,
        "page": 522,
        "ruku": 457,
        "hizbQuarter": 209,
        "sajda": false
      }
    ],
    "surahs": {
      "51": {
        "number": 51,
        "name": "سُورَةُ الذَّارِيَاتِ",
        "englishName": "Adh-Dhaariyat",
        "englishNameTranslation": "The Winnowing Winds",
        "revelationType": "Meccan",
        "numberOfAyahs": 60
      }
    },
    "edition": {
      "identifier": "fr.hamidullah",
      "language": "fr",
      "name": "Hamidullah",
      "englishName": "Muhammad Hamidullah",
      "format": "text",
      "type": "translation",
      "direction": "ltr"
    }
  }
}