{
  "code": 200,
  "status": "OK",
  "data": {
    "number": 557,
    "ayahs": [
      {
        "number": 5209,
        "text": "Et ceux qui ont mécru et traité de mensonges Nos versets, ceux-là sont les gens du Feu où ils demeureront éternellement. Et quelle mauvaise destination!",
        "surah": {
          "number": 64,
          "name": "سُورَةُ التَّغَابُنِ",
          "englishName": "At-Taghaabun",
          "englishNameTranslation": "Mutual Disillusion",
          "revelationType": "Medinan",
          "numberOfAyahs": 18
        },
        "numberInSurah": 10,
        "juz": 28,
        "manzil": 7,
        "page": 557,
        "ruku": 490,
        "hizbQuarter": 222,
        "sajda": false
      },
      {
        "number": 5210,
        "text": "Nul malheur n'atteint [l'homme] que par la permission d'Allah. Et quiconque croit en Allah, [Allah] guide son cœur. Allah est Omniscient.",
        "surah": {
          "number": 64,
          "name": "سُورَةُ التَّغَابُنِ",
          "englishName": "At-Taghaabun",
          "englishNameTranslation": "Mutual Disillusion",
          "revelationType": "Medinan",
          "numberOfAyahs": 18
        },
        "numberInSurah": 11,
        "juz": 28,
        "manzil": 7,
        "page": 557,
        "ruku": 491,
        "hizbQuarter": 222,
        "sajda": false
      },
      {
        "number": 5211,
        "text": "Obéissez à Allah et obéissez au Messager et si vous vous détournez... il n'incombe à Notre messager que de transmettre en clair (son message).",
        "surah": {
          "number": 64,
          "name": "سُورَةُ التَّغَابُنِ",
          "englishName": "At-Taghaabun",
          "englishNameTranslation": "Mutual Disillusion",
          "revelationType": "Medinan",
          "numberOfAyahs": 18
        },
        "numberInSurah": 12,
        "juz": 28,
        "manzil": 7,
        "page": 557,
        "ruku": 491,
        "hizbQuarter": 222,
        "sajda": false
      },
      {
        "number": 5212,
        "text": "Allah nulle autre divinité que Lui! Et c'est à Allah que les croyants [doivent] s'en remettre.",
        "surah": {
          "number": 64,
          "name": "سُورَةُ التَّغَابُنِ",
          "englishName": "At-Taghaabun",
          "englishNameTranslation": "Mutual Disillusion",
          "revelationType": "Medinan",
          "numberOfAyahs": 18
        },
        "numberInSurah": 13,
        "juz": 28,
        "manzil": 7,
        "page": 557,
        "ruku": 491,
        "hizbQuarter": 222,
        "sajda": false
      },
      {
        "number": 5213,
        "text": "O vous qui avez cru, vous avez de vos épouses et de vos enfants un ennemi [une tentation]. Prenez-y garde donc. Mais si vous [les] excusez, passez sur [leurs] fautes et [leur] pardonnez, sachez qu'Allah est Pardonneur, Très Miséricordieux.",
        "surah": {
          "number": 64,
          "name": "سُورَةُ التَّغَابُنِ",
          "englishName": "At-Taghaabun",
          "englishNameTranslation": "Mutual Disillusion",
          "revelationType": "Medinan",
          "numberOfAyahs": 18
        },
        "numberInSurah": 14,
        "juz": 28,
        "manzil": 7,
        "page": 557,
        "ruku": 491,
        "hizbQuarter": 222,
        "sajda": false
      },
      {
        "number": 5214,
        "text": "Vos biens et vos enfants ne sont qu'une tentation, alors qu'auprès d'Allah est une énorme récompense.",
        "surah": {
          "number": 64,
          "name": "سُورَةُ التَّغَابُنِ",
          "englishName": "At-Taghaabun",
          "englishNameTranslation": "Mutual Disillusion",
          "revelationType": "Medinan",
          "numberOfAyahs": 18
        },
        "numberInSurah": 15,
        "juz": 28,
        "manzil": 7,
        "page": 557,
        "ruku": 491,
        "hizbQuarter": 222,
        "sajda": false
      },
      {
        "number": 5215,
        "text": "Craignez Allah, donc autant que vous pouvez, écoutez, obéissez et faites largesses. Ce sera un bien pour vous. Et quiconque a été protégé contre sa propre avidité... ceux-là sont ceux qui réussissent.",
        "surah": {
          "number": 64,
          "name": "سُورَةُ التَّغَابُنِ",
          "englishName": "At-Taghaabun",
          "englishNameTranslation": "Mutual Disillusion",
          "revelationType": "Medinan",
          "numberOfAyahs": 18
        },
        "numberInSurah": 16,
        "juz": 28,
        "manzil": 7,
        "page": 557,
        "ruku": 491,
        "hizbQuarter": 222,
        "sajda": false
      },
      {
        "number": 5216,
        "text": "Si vous faites à Allah un prêt sincère, Il le multipliera pour vous et vous pardonnera. Allah cependant est très Reconnaissant et Indulgent.",
        "surah": {
          "number": 64,
          "name": "سُورَةُ التَّغَابُنِ",
          "englishName": "At-Taghaabun",
          "englishNameTranslation": "Mutual Disillusion",
          "revelationType": "Medinan",
          "numberOfAyahs": 18
        },
        "numberInSurah": 17,
        "juz": 28,
        "manzil": 7,
        "page": 557,
        "ruku": 491,
        "hizbQuarter": 222,
        "sajda": false
      },
      {
        "number": 5217,
        "text": "Il est le Connaisseur du monde Invisible et visible, et Il est le Puissant, le Sage.",
        "surah": {
          "number": 64,
          "name": "سُورَةُ التَّغَابُنِ",
          "englishName": "At-Taghaabun",
          "englishNameTranslation": "Mutual Disillusion",
          "revelationType": "Medinan",
          "numberOfAyahs": 18
        },
        "numberInSurah": 18,
        "juz": 28,
        "manzil": 7,
        "page": 557,
        "ruku": 491,
        "hizbQuarter": 222,
        "sajda": false
      }
    ],
    "surahs": {
      "64": {
        "number": 64,
        "name": "سُورَةُ التَّغَابُنِ",
        "englishName": "At-Taghaabun",
        "englishNameTranslation": "Mutual Disillusion",
        "revelationType": "Medinan",
        "numberOfAyahs": 18
      }
    },
    "edition": {
      "identifier": "fr.hamidullah",
      "language": "fr",
      "name": "Hamidullah",
      "englishName": "Muhammad Hamidullah",
      "format": "text",
      "type": "translation",
      "direction": "ltr"
    }
  }
}