{
  "code": 200,
  "status": "OK",
  "data": {
    "number": 292,
    "ayahs": [
      {
        "number": 2126,
        "text": "ومن يهده الله فهو المهتدي إلى الحق، ومن يضلله فيخذلْه ويَكِلْه إلى نفسه فلا هادي له من دون الله، وهؤلاء الضُّلال يبعثهم الله يوم القيامة، ويحشرهم على وجوههم، وهم لا يرون ولا ينطقون ولا يسمعون، مصيرهم إلى نار جهنم الملتهبة، كلما سكن لهيبها، وخمدت نارها، زدناهم نارًا ملتهبة متأججة.",
        "surah": {
          "number": 17,
          "name": "سُورَةُ الإِسۡرَاءِ",
          "englishName": "Al-Israa",
          "englishNameTranslation": "The Night Journey",
          "revelationType": "Meccan",
          "numberOfAyahs": 111
        },
        "numberInSurah": 97,
        "juz": 15,
        "manzil": 4,
        "page": 292,
        "ruku": 250,
        "hizbQuarter": 116,
        "sajda": false
      },
      {
        "number": 2127,
        "text": "هذا الذي وُصِف من العذاب عقاب للمشركين؛ بسبب كفرهم بآيات الله وحججه، وتكذيبهم رسله الذين دَعَوْهم إلى عبادته، وقولهم استنكارًا - إذا أُمروا بالتصديق بالبعث -: أإذا متنا وصِرْنا عظامًا بالية وأجزاءً متفتتة نُبعث بعد ذلك خَلْقًا جديدًا؟",
        "surah": {
          "number": 17,
          "name": "سُورَةُ الإِسۡرَاءِ",
          "englishName": "Al-Israa",
          "englishNameTranslation": "The Night Journey",
          "revelationType": "Meccan",
          "numberOfAyahs": 111
        },
        "numberInSurah": 98,
        "juz": 15,
        "manzil": 4,
        "page": 292,
        "ruku": 250,
        "hizbQuarter": 116,
        "sajda": false
      },
      {
        "number": 2128,
        "text": "أَغَفَل هؤلاء المشركون، فلم يتبصروا ويعلموا أن الله الذي خلق السموات والأرض وما فيهن من المخلوقات على غير مثال سابق، قادر على أن يخلق أمثالهم بعد فنائهم؟ وقد جعل الله لهؤلاء المشركين وقتًا محددًا لموتهم وعذابهم، لا شك أنه آتيهم، ومع وضوح الحق ودلائله أبى الكافرون إلا جحودًا لدين الله عزَّ وجلَّ.",
        "surah": {
          "number": 17,
          "name": "سُورَةُ الإِسۡرَاءِ",
          "englishName": "Al-Israa",
          "englishNameTranslation": "The Night Journey",
          "revelationType": "Meccan",
          "numberOfAyahs": 111
        },
        "numberInSurah": 99,
        "juz": 15,
        "manzil": 4,
        "page": 292,
        "ruku": 250,
        "hizbQuarter": 117,
        "sajda": false
      },
      {
        "number": 2129,
        "text": "قل -أيها الرسول- لهؤلاء المشركين: لو كنتم تملكون خزائن رحمة ربي التي لا تنفد ولا تبيد إذًا لبخلتم بها، فلم تعطوا منها غيركم خوفًا مِن نفادها فتصبحوا فقراء. ومن شأن الإنسان أنه بخيل بما في يده إلا مَن عصم الله بالإيمان.",
        "surah": {
          "number": 17,
          "name": "سُورَةُ الإِسۡرَاءِ",
          "englishName": "Al-Israa",
          "englishNameTranslation": "The Night Journey",
          "revelationType": "Meccan",
          "numberOfAyahs": 111
        },
        "numberInSurah": 100,
        "juz": 15,
        "manzil": 4,
        "page": 292,
        "ruku": 250,
        "hizbQuarter": 117,
        "sajda": false
      },
      {
        "number": 2130,
        "text": "ولقد آتينا موسى تسع معجزات واضحات شاهدات على صِدْق نبوته وهي: العصا واليد والسنون ونقص الثمرات والطوفان والجراد والقمل والضفادع والدم، فاسأل -أيها الرسول- اليهود سؤال تقرير حين جاء موسى أسلافهم بمعجزاته الواضحات، فقال فرعون لموسى: إني لأظنك -يا موسى- ساحرا، مخدوعًا مغلوبًا على عقلك بما تأتيه من غرائب الأفعال.",
        "surah": {
          "number": 17,
          "name": "سُورَةُ الإِسۡرَاءِ",
          "englishName": "Al-Israa",
          "englishNameTranslation": "The Night Journey",
          "revelationType": "Meccan",
          "numberOfAyahs": 111
        },
        "numberInSurah": 101,
        "juz": 15,
        "manzil": 4,
        "page": 292,
        "ruku": 251,
        "hizbQuarter": 117,
        "sajda": false
      },
      {
        "number": 2131,
        "text": "فردَّ عليه موسى: لقد تيقَّنتَ -يا فرعون- أنه ما أنزل تلك المعجزات التسع الشاهدة على صدق نبوتي إلا رب السموات والأرض؛ لتكون دلالات يَستدِل بها أولو البصائر على وحدانية الله تعالى في ربوبيته وألوهيته، وإني لعلى يقين أنك -يا فرعون- هالك ملعون مغلوب.",
        "surah": {
          "number": 17,
          "name": "سُورَةُ الإِسۡرَاءِ",
          "englishName": "Al-Israa",
          "englishNameTranslation": "The Night Journey",
          "revelationType": "Meccan",
          "numberOfAyahs": 111
        },
        "numberInSurah": 102,
        "juz": 15,
        "manzil": 4,
        "page": 292,
        "ruku": 251,
        "hizbQuarter": 117,
        "sajda": false
      },
      {
        "number": 2132,
        "text": "فأراد فرعون أن يزعج موسى ويخرجه مع بني إسرائيل مِن أرض \"مصر\"، فأغرقناه ومَن معه مِن جندٍ في البحر عقابًا لهم.",
        "surah": {
          "number": 17,
          "name": "سُورَةُ الإِسۡرَاءِ",
          "englishName": "Al-Israa",
          "englishNameTranslation": "The Night Journey",
          "revelationType": "Meccan",
          "numberOfAyahs": 111
        },
        "numberInSurah": 103,
        "juz": 15,
        "manzil": 4,
        "page": 292,
        "ruku": 251,
        "hizbQuarter": 117,
        "sajda": false
      },
      {
        "number": 2133,
        "text": "وقلنا من بعد هلاك فرعون وجنده لبني إسرائيل: اسكنوا أرض \"الشام\"، فإذا جاء يوم القيامة جئنا بكم جميعًا مِن قبوركم إلى موقف الحساب.",
        "surah": {
          "number": 17,
          "name": "سُورَةُ الإِسۡرَاءِ",
          "englishName": "Al-Israa",
          "englishNameTranslation": "The Night Journey",
          "revelationType": "Meccan",
          "numberOfAyahs": 111
        },
        "numberInSurah": 104,
        "juz": 15,
        "manzil": 4,
        "page": 292,
        "ruku": 251,
        "hizbQuarter": 117,
        "sajda": false
      }
    ],
    "surahs": {
      "17": {
        "number": 17,
        "name": "سُورَةُ الإِسۡرَاءِ",
        "englishName": "Al-Israa",
        "englishNameTranslation": "The Night Journey",
        "revelationType": "Meccan",
        "numberOfAyahs": 111
      }
    },
    "edition": {
      "identifier": "ar.muyassar",
      "language": "ar",
      "name": "تفسير المیسر",
      "englishName": "King Fahad Quran Complex",
      "format": "text",
      "type": "tafsir",
      "direction": "rtl"
    }
  }
}