{
  "code": 200,
  "status": "OK",
  "data": {
    "number": 379,
    "ayahs": [
      {
        "number": 3182,
        "text": "إني وجدت امرأةً تحكم أهل \"سبأ\"، وأوتيت من كل شيء من أسباب الدنيا، ولها سرير عظيم القدر، تجلس عليه لإدارة ملكها.",
        "surah": {
          "number": 27,
          "name": "سُورَةُ النَّمۡلِ",
          "englishName": "An-Naml",
          "englishNameTranslation": "The Ant",
          "revelationType": "Meccan",
          "numberOfAyahs": 93
        },
        "numberInSurah": 23,
        "juz": 19,
        "manzil": 5,
        "page": 379,
        "ruku": 328,
        "hizbQuarter": 151,
        "sajda": false
      },
      {
        "number": 3183,
        "text": "وجدتُها هي وقومها يعبدون الشمس معرضين عن عبادة الله، وحسَّن لهم الشيطان أعمالهم السيئة التي كانوا يعملونها، فصرفهم عن الإيمان بالله وتوحيده، فهم لا يهتدون إلى الله وتوحيده وعبادته وحده.",
        "surah": {
          "number": 27,
          "name": "سُورَةُ النَّمۡلِ",
          "englishName": "An-Naml",
          "englishNameTranslation": "The Ant",
          "revelationType": "Meccan",
          "numberOfAyahs": 93
        },
        "numberInSurah": 24,
        "juz": 19,
        "manzil": 5,
        "page": 379,
        "ruku": 328,
        "hizbQuarter": 151,
        "sajda": false
      },
      {
        "number": 3184,
        "text": "حسَّن لهم الشيطان ذلك؛ لئلا يسجدوا لله الذي يُخرج المخبوء المستور في السموات والأرض من المطر والنبات وغير ذلك، ويعلم ما تُسرُّون وما تظهرون. الله الذي لا معبود يستحق العبادة سواه، رب العرش العظيم.",
        "surah": {
          "number": 27,
          "name": "سُورَةُ النَّمۡلِ",
          "englishName": "An-Naml",
          "englishNameTranslation": "The Ant",
          "revelationType": "Meccan",
          "numberOfAyahs": 93
        },
        "numberInSurah": 25,
        "juz": 19,
        "manzil": 5,
        "page": 379,
        "ruku": 328,
        "hizbQuarter": 151,
        "sajda": false
      },
      {
        "number": 3185,
        "text": "حسَّن لهم الشيطان ذلك؛ لئلا يسجدوا لله الذي يُخرج المخبوء المستور في السموات والأرض من المطر والنبات وغير ذلك، ويعلم ما تُسرُّون وما تظهرون. الله الذي لا معبود يستحق العبادة سواه، رب العرش العظيم.",
        "surah": {
          "number": 27,
          "name": "سُورَةُ النَّمۡلِ",
          "englishName": "An-Naml",
          "englishNameTranslation": "The Ant",
          "revelationType": "Meccan",
          "numberOfAyahs": 93
        },
        "numberInSurah": 26,
        "juz": 19,
        "manzil": 5,
        "page": 379,
        "ruku": 328,
        "hizbQuarter": 151,
        "sajda": {
          "id": 9,
          "recommended": true,
          "obligatory": false
        }
      },
      {
        "number": 3186,
        "text": "قال سليمان للهدهد: سنتأمل فيما جئتنا به من الخبر أصدقت في ذلك أم كنت من الكاذبين فيه؟ اذهب بكتابي هذا إلى أهل \"سبأ\" فأعطهم إياه، ثم تنحَّ عنهم قريبًا منهم بحيث تسمع كلامهم، فتأمل ما يتردد بينهم من الكلام.",
        "surah": {
          "number": 27,
          "name": "سُورَةُ النَّمۡلِ",
          "englishName": "An-Naml",
          "englishNameTranslation": "The Ant",
          "revelationType": "Meccan",
          "numberOfAyahs": 93
        },
        "numberInSurah": 27,
        "juz": 19,
        "manzil": 5,
        "page": 379,
        "ruku": 328,
        "hizbQuarter": 152,
        "sajda": false
      },
      {
        "number": 3187,
        "text": "قال سليمان للهدهد: سنتأمل فيما جئتنا به من الخبر أصدقت في ذلك أم كنت من الكاذبين فيه؟ اذهب بكتابي هذا إلى أهل \"سبأ\" فأعطهم إياه، ثم تنحَّ عنهم قريبًا منهم بحيث تسمع كلامهم، فتأمل ما يتردد بينهم من الكلام.",
        "surah": {
          "number": 27,
          "name": "سُورَةُ النَّمۡلِ",
          "englishName": "An-Naml",
          "englishNameTranslation": "The Ant",
          "revelationType": "Meccan",
          "numberOfAyahs": 93
        },
        "numberInSurah": 28,
        "juz": 19,
        "manzil": 5,
        "page": 379,
        "ruku": 328,
        "hizbQuarter": 152,
        "sajda": false
      },
      {
        "number": 3188,
        "text": "ذهب الهدهد وألقى الكتاب إلى الملكة فقرأته، فجمعت أشراف قومها، وسمعها تقول لهم: إني وصل إليَّ كتاب جليل المقدار من شخص عظيم الشأن.",
        "surah": {
          "number": 27,
          "name": "سُورَةُ النَّمۡلِ",
          "englishName": "An-Naml",
          "englishNameTranslation": "The Ant",
          "revelationType": "Meccan",
          "numberOfAyahs": 93
        },
        "numberInSurah": 29,
        "juz": 19,
        "manzil": 5,
        "page": 379,
        "ruku": 328,
        "hizbQuarter": 152,
        "sajda": false
      },
      {
        "number": 3189,
        "text": "ثم بيَّنت ما فيه فقالت: إنه من سليمان، وإنه مفتتح بـ \"بسم الله الرحمن الرحيم\" ألا تتكبروا ولا تتعاظموا عما دعوتكم إليه، وأقْبِلوا إليَّ منقادين لله بالوحدانية والطاعة مسلمين له.",
        "surah": {
          "number": 27,
          "name": "سُورَةُ النَّمۡلِ",
          "englishName": "An-Naml",
          "englishNameTranslation": "The Ant",
          "revelationType": "Meccan",
          "numberOfAyahs": 93
        },
        "numberInSurah": 30,
        "juz": 19,
        "manzil": 5,
        "page": 379,
        "ruku": 328,
        "hizbQuarter": 152,
        "sajda": false
      },
      {
        "number": 3190,
        "text": "ثم بيَّنت ما فيه فقالت: إنه من سليمان، وإنه مفتتح بـ \"بسم الله الرحمن الرحيم\" ألا تتكبروا ولا تتعاظموا عما دعوتكم إليه، وأقْبِلوا إليَّ منقادين لله بالوحدانية والطاعة مسلمين له.",
        "surah": {
          "number": 27,
          "name": "سُورَةُ النَّمۡلِ",
          "englishName": "An-Naml",
          "englishNameTranslation": "The Ant",
          "revelationType": "Meccan",
          "numberOfAyahs": 93
        },
        "numberInSurah": 31,
        "juz": 19,
        "manzil": 5,
        "page": 379,
        "ruku": 328,
        "hizbQuarter": 152,
        "sajda": false
      },
      {
        "number": 3191,
        "text": "قالت: يا أيها الأشراف أشيروا عليَّ في هذا الأمر، ما كنت لأفصل في أمر إلا بمحضركم ومشورتكم.",
        "surah": {
          "number": 27,
          "name": "سُورَةُ النَّمۡلِ",
          "englishName": "An-Naml",
          "englishNameTranslation": "The Ant",
          "revelationType": "Meccan",
          "numberOfAyahs": 93
        },
        "numberInSurah": 32,
        "juz": 19,
        "manzil": 5,
        "page": 379,
        "ruku": 329,
        "hizbQuarter": 152,
        "sajda": false
      },
      {
        "number": 3192,
        "text": "قالوا مجيبين لها: نحن أصحاب قوة في العدد والعُدَّة وأصحاب النجدة والشجاعة في شدة الحرب، والأمر موكول إليكِ، وأنتِ صاحبة الرأي، فتأملي ماذا تأمريننا به؟ فنحن سامعون لأمرك مطيعون لك.",
        "surah": {
          "number": 27,
          "name": "سُورَةُ النَّمۡلِ",
          "englishName": "An-Naml",
          "englishNameTranslation": "The Ant",
          "revelationType": "Meccan",
          "numberOfAyahs": 93
        },
        "numberInSurah": 33,
        "juz": 19,
        "manzil": 5,
        "page": 379,
        "ruku": 329,
        "hizbQuarter": 152,
        "sajda": false
      },
      {
        "number": 3193,
        "text": "قالت محذرةً لهم من مواجهة سليمان بالعداوة، ومبيِّنة لهم سوء مغبَّة القتال: إن الملوك إذا دخلوا بجيوشهم قريةً عنوةً وقهرًا خرَّبوها وصيَّروا أعزَّة أهلها أذلة، وقتلوا وأسروا، وهذه عادتهم المستمرة الثابتة لحمل الناس على أن يهابوهم. وإني مرسلة إلى سليمان وقومه بهديَّة مشتملة على نفائس الأموال أصانعه بها، ومنتظرة ما يرجع به الرسل.",
        "surah": {
          "number": 27,
          "name": "سُورَةُ النَّمۡلِ",
          "englishName": "An-Naml",
          "englishNameTranslation": "The Ant",
          "revelationType": "Meccan",
          "numberOfAyahs": 93
        },
        "numberInSurah": 34,
        "juz": 19,
        "manzil": 5,
        "page": 379,
        "ruku": 329,
        "hizbQuarter": 152,
        "sajda": false
      },
      {
        "number": 3194,
        "text": "قالت محذرةً لهم من مواجهة سليمان بالعداوة، ومبيِّنة لهم سوء مغبَّة القتال: إن الملوك إذا دخلوا بجيوشهم قريةً عنوةً وقهرًا خرَّبوها وصيَّروا أعزَّة أهلها أذلة، وقتلوا وأسروا، وهذه عادتهم المستمرة الثابتة لحمل الناس على أن يهابوهم. وإني مرسلة إلى سليمان وقومه بهديَّة مشتملة على نفائس الأموال أصانعه بها، ومنتظرة ما يرجع به الرسل.",
        "surah": {
          "number": 27,
          "name": "سُورَةُ النَّمۡلِ",
          "englishName": "An-Naml",
          "englishNameTranslation": "The Ant",
          "revelationType": "Meccan",
          "numberOfAyahs": 93
        },
        "numberInSurah": 35,
        "juz": 19,
        "manzil": 5,
        "page": 379,
        "ruku": 329,
        "hizbQuarter": 152,
        "sajda": false
      }
    ],
    "surahs": {
      "27": {
        "number": 27,
        "name": "سُورَةُ النَّمۡلِ",
        "englishName": "An-Naml",
        "englishNameTranslation": "The Ant",
        "revelationType": "Meccan",
        "numberOfAyahs": 93
      }
    },
    "edition": {
      "identifier": "ar.muyassar",
      "language": "ar",
      "name": "تفسير المیسر",
      "englishName": "King Fahad Quran Complex",
      "format": "text",
      "type": "tafsir",
      "direction": "rtl"
    }
  }
}