{
  "code": 200,
  "status": "OK",
  "data": {
    "number": 563,
    "ayahs": [
      {
        "number": 5254,
        "text": "وأخفوا قولكم- أيها الناس- في أي أمر من أموركم أو أعلنوه، فهما عند الله سواء، إنه سبحانه عليم بمضمرات الصدور، فكيف تخفى عليه أقوالكم وأعمالكم؟",
        "surah": {
          "number": 67,
          "name": "سُورَةُ المُلۡكِ",
          "englishName": "Al-Mulk",
          "englishNameTranslation": "The Sovereignty",
          "revelationType": "Meccan",
          "numberOfAyahs": 30
        },
        "numberInSurah": 13,
        "juz": 29,
        "manzil": 7,
        "page": 563,
        "ruku": 496,
        "hizbQuarter": 225,
        "sajda": false
      },
      {
        "number": 5255,
        "text": "ألا يعلم ربُّ العالمين خَلْقه وشؤونهم، وهو الذي خَلَقهم وأتقن خَلْقَهُمْ وأحسنه؟ وهو اللطيف بعباده، الخبير بهم وبأعمالهم.",
        "surah": {
          "number": 67,
          "name": "سُورَةُ المُلۡكِ",
          "englishName": "Al-Mulk",
          "englishNameTranslation": "The Sovereignty",
          "revelationType": "Meccan",
          "numberOfAyahs": 30
        },
        "numberInSurah": 14,
        "juz": 29,
        "manzil": 7,
        "page": 563,
        "ruku": 496,
        "hizbQuarter": 225,
        "sajda": false
      },
      {
        "number": 5256,
        "text": "الله وحده هو الذي جعل لكم الأرض سهلة ممهدة تستقرون عليها، فامشوا في نواحيها وجوانبها، وكلوا من رزق الله الذي يخرجه لكم منها، وإليه وحده البعث من قبوركم للحساب والجزاء. وفي الآية إيماء إلى طلب الرزق والمكاسب، وفيها دلالة على أن الله هو الإله الحق وحده لا شريك له، وعلى قدرته، والتذكير بنعمه، والتحذير من الركون إلى الدنيا.",
        "surah": {
          "number": 67,
          "name": "سُورَةُ المُلۡكِ",
          "englishName": "Al-Mulk",
          "englishNameTranslation": "The Sovereignty",
          "revelationType": "Meccan",
          "numberOfAyahs": 30
        },
        "numberInSurah": 15,
        "juz": 29,
        "manzil": 7,
        "page": 563,
        "ruku": 497,
        "hizbQuarter": 225,
        "sajda": false
      },
      {
        "number": 5257,
        "text": "هل أمنتم- يا كفار \"مكة\"- الله الذي فوق السماء أن يخسف بكم الأرض، فإذا هي تضطرب بكم حتى تهلكوا؟ هل أمنتم الله الذي فوق السماء أن يرسل عليكم ريحا ترجمكم بالحجارة الصغيرة، فستعلمون- أيها الكافرون- كيف تحذيري لكم إذا عاينتم العذاب؟ ولا ينفعكم العلم حين ذلك. وفي الآية إثبات العلو لله تعالى، كما يليق بجلاله سبحانه.",
        "surah": {
          "number": 67,
          "name": "سُورَةُ المُلۡكِ",
          "englishName": "Al-Mulk",
          "englishNameTranslation": "The Sovereignty",
          "revelationType": "Meccan",
          "numberOfAyahs": 30
        },
        "numberInSurah": 16,
        "juz": 29,
        "manzil": 7,
        "page": 563,
        "ruku": 497,
        "hizbQuarter": 225,
        "sajda": false
      },
      {
        "number": 5258,
        "text": "هل أمنتم- يا كفار \"مكة\"- الله الذي فوق السماء أن يخسف بكم الأرض، فإذا هي تضطرب بكم حتى تهلكوا؟ هل أمنتم الله الذي فوق السماء أن يرسل عليكم ريحا ترجمكم بالحجارة الصغيرة، فستعلمون- أيها الكافرون- كيف تحذيري لكم إذا عاينتم العذاب؟ ولا ينفعكم العلم حين ذلك. وفي الآية إثبات العلو لله تعالى، كما يليق بجلاله سبحانه.",
        "surah": {
          "number": 67,
          "name": "سُورَةُ المُلۡكِ",
          "englishName": "Al-Mulk",
          "englishNameTranslation": "The Sovereignty",
          "revelationType": "Meccan",
          "numberOfAyahs": 30
        },
        "numberInSurah": 17,
        "juz": 29,
        "manzil": 7,
        "page": 563,
        "ruku": 497,
        "hizbQuarter": 225,
        "sajda": false
      },
      {
        "number": 5259,
        "text": "ولقد كذَّب الذين كانوا قبل كفار \"مكة\" كقوم نوح وعاد وثمود رسلهم، فكيف كان إنكاري عليهم، وتغييري ما بهم من نعمة بإنزال العذاب بهم وإهلاكهم؟",
        "surah": {
          "number": 67,
          "name": "سُورَةُ المُلۡكِ",
          "englishName": "Al-Mulk",
          "englishNameTranslation": "The Sovereignty",
          "revelationType": "Meccan",
          "numberOfAyahs": 30
        },
        "numberInSurah": 18,
        "juz": 29,
        "manzil": 7,
        "page": 563,
        "ruku": 497,
        "hizbQuarter": 225,
        "sajda": false
      },
      {
        "number": 5260,
        "text": "أغَفَل هؤلاء الكافرون، ولم ينظروا إلى الطير فوقهم، باسطات أجنحتها عند طيرانها في الهواء، ويضممنها إلى جُنوبها أحيانًا؟ ما يحفظها من الوقوع عند ذلك إلا الرحمن. إنه بكل شيء بصير لا يُرى في خلقه نقص ولا تفاوت. بل مَن هذا الذي هو في زعمكم- أيها الكافرون- حزب لكم ينصركم من غير الرحمن، إن أراد بكم سوءًا؟ ما الكافرون في زعمهم هذا إلا في خداع وضلال من الشيطان. بل مَن هذا الرازق المزعوم الذي يرزقكم إن أمسك الله رزقه ومنعه عنكم؟ بل استمر الكافرون في طغيانهم وضلالهم في معاندة واستكبار ونفور عن الحق، لا يسمعون له، ولا يتبعونه.",
        "surah": {
          "number": 67,
          "name": "سُورَةُ المُلۡكِ",
          "englishName": "Al-Mulk",
          "englishNameTranslation": "The Sovereignty",
          "revelationType": "Meccan",
          "numberOfAyahs": 30
        },
        "numberInSurah": 19,
        "juz": 29,
        "manzil": 7,
        "page": 563,
        "ruku": 497,
        "hizbQuarter": 225,
        "sajda": false
      },
      {
        "number": 5261,
        "text": "أغَفَل هؤلاء الكافرون، ولم ينظروا إلى الطير فوقهم، باسطات أجنحتها عند طيرانها في الهواء، ويضممنها إلى جُنوبها أحيانًا؟ ما يحفظها من الوقوع عند ذلك إلا الرحمن. إنه بكل شيء بصير لا يُرى في خلقه نقص ولا تفاوت. بل مَن هذا الذي هو في زعمكم- أيها الكافرون- حزب لكم ينصركم من غير الرحمن، إن أراد بكم سوءًا؟ ما الكافرون في زعمهم هذا إلا في خداع وضلال من الشيطان. بل مَن هذا الرازق المزعوم الذي يرزقكم إن أمسك الله رزقه ومنعه عنكم؟ بل استمر الكافرون في طغيانهم وضلالهم في معاندة واستكبار ونفور عن الحق، لا يسمعون له، ولا يتبعونه.",
        "surah": {
          "number": 67,
          "name": "سُورَةُ المُلۡكِ",
          "englishName": "Al-Mulk",
          "englishNameTranslation": "The Sovereignty",
          "revelationType": "Meccan",
          "numberOfAyahs": 30
        },
        "numberInSurah": 20,
        "juz": 29,
        "manzil": 7,
        "page": 563,
        "ruku": 497,
        "hizbQuarter": 225,
        "sajda": false
      },
      {
        "number": 5262,
        "text": "أغَفَل هؤلاء الكافرون، ولم ينظروا إلى الطير فوقهم، باسطات أجنحتها عند طيرانها في الهواء، ويضممنها إلى جُنوبها أحيانًا؟ ما يحفظها من الوقوع عند ذلك إلا الرحمن. إنه بكل شيء بصير لا يُرى في خلقه نقص ولا تفاوت. بل مَن هذا الذي هو في زعمكم- أيها الكافرون- حزب لكم ينصركم من غير الرحمن، إن أراد بكم سوءًا؟ ما الكافرون في زعمهم هذا إلا في خداع وضلال من الشيطان. بل مَن هذا الرازق المزعوم الذي يرزقكم إن أمسك الله رزقه ومنعه عنكم؟ بل استمر الكافرون في طغيانهم وضلالهم في معاندة واستكبار ونفور عن الحق، لا يسمعون له، ولا يتبعونه.",
        "surah": {
          "number": 67,
          "name": "سُورَةُ المُلۡكِ",
          "englishName": "Al-Mulk",
          "englishNameTranslation": "The Sovereignty",
          "revelationType": "Meccan",
          "numberOfAyahs": 30
        },
        "numberInSurah": 21,
        "juz": 29,
        "manzil": 7,
        "page": 563,
        "ruku": 497,
        "hizbQuarter": 225,
        "sajda": false
      },
      {
        "number": 5263,
        "text": "أفمن يمشي منكَّسًا على وجهه لا يدري أين يسلك ولا كيف يذهب، أشد استقامة على الطريق وأهدى، أَمَّن يمشي مستويًا منتصب القامة سالمًا على طريق واضح لا اعوجاج فيه؟ وهذا مثل ضربه الله للكافر والمؤمن.",
        "surah": {
          "number": 67,
          "name": "سُورَةُ المُلۡكِ",
          "englishName": "Al-Mulk",
          "englishNameTranslation": "The Sovereignty",
          "revelationType": "Meccan",
          "numberOfAyahs": 30
        },
        "numberInSurah": 22,
        "juz": 29,
        "manzil": 7,
        "page": 563,
        "ruku": 497,
        "hizbQuarter": 225,
        "sajda": false
      },
      {
        "number": 5264,
        "text": "قل لهم -أيها الرسول-: الله هو الذي أوجدكم من العدم، وجعل لكم السمع لتسمعوا به، والأبصار لتبصروا بها، والقلوب لتعقلوا بها، قليلا- أيها الكافرون- ما تؤدون شكر هذه النعم لربكم الذي أنعم بها عليكم. قل لهم: الله هو الذي خلقكم ونشركم في الأرض، وإليه وحده تُجمعون بعد هذا التفرق للحساب والجزاء.",
        "surah": {
          "number": 67,
          "name": "سُورَةُ المُلۡكِ",
          "englishName": "Al-Mulk",
          "englishNameTranslation": "The Sovereignty",
          "revelationType": "Meccan",
          "numberOfAyahs": 30
        },
        "numberInSurah": 23,
        "juz": 29,
        "manzil": 7,
        "page": 563,
        "ruku": 497,
        "hizbQuarter": 225,
        "sajda": false
      },
      {
        "number": 5265,
        "text": "قل لهم -أيها الرسول-: الله هو الذي أوجدكم من العدم، وجعل لكم السمع لتسمعوا به، والأبصار لتبصروا بها، والقلوب لتعقلوا بها، قليلا- أيها الكافرون- ما تؤدون شكر هذه النعم لربكم الذي أنعم بها عليكم. قل لهم: الله هو الذي خلقكم ونشركم في الأرض، وإليه وحده تُجمعون بعد هذا التفرق للحساب والجزاء.",
        "surah": {
          "number": 67,
          "name": "سُورَةُ المُلۡكِ",
          "englishName": "Al-Mulk",
          "englishNameTranslation": "The Sovereignty",
          "revelationType": "Meccan",
          "numberOfAyahs": 30
        },
        "numberInSurah": 24,
        "juz": 29,
        "manzil": 7,
        "page": 563,
        "ruku": 497,
        "hizbQuarter": 225,
        "sajda": false
      },
      {
        "number": 5266,
        "text": "ويقول الكافرون: متى يتحقق هذا الوعد بالحشر يا محمد؟ أخبرونا بزمانه أيها المؤمنون، إن كنتم صادقين فيما تدَّعون، قل -أيها الرسول- لهؤلاء: إن العلم بوقت قيام الساعة اختصَّ الله به، وإنما أنا نذير لكم أخوِّفكم عاقبة كفركم، وأبيِّن لكم ما أمرني الله ببيانه غاية البيان.",
        "surah": {
          "number": 67,
          "name": "سُورَةُ المُلۡكِ",
          "englishName": "Al-Mulk",
          "englishNameTranslation": "The Sovereignty",
          "revelationType": "Meccan",
          "numberOfAyahs": 30
        },
        "numberInSurah": 25,
        "juz": 29,
        "manzil": 7,
        "page": 563,
        "ruku": 497,
        "hizbQuarter": 225,
        "sajda": false
      },
      {
        "number": 5267,
        "text": "ويقول الكافرون: متى يتحقق هذا الوعد بالحشر يا محمد؟ أخبرونا بزمانه أيها المؤمنون، إن كنتم صادقين فيما تدَّعون، قل -أيها الرسول- لهؤلاء: إن العلم بوقت قيام الساعة اختصَّ الله به، وإنما أنا نذير لكم أخوِّفكم عاقبة كفركم، وأبيِّن لكم ما أمرني الله ببيانه غاية البيان.",
        "surah": {
          "number": 67,
          "name": "سُورَةُ المُلۡكِ",
          "englishName": "Al-Mulk",
          "englishNameTranslation": "The Sovereignty",
          "revelationType": "Meccan",
          "numberOfAyahs": 30
        },
        "numberInSurah": 26,
        "juz": 29,
        "manzil": 7,
        "page": 563,
        "ruku": 497,
        "hizbQuarter": 225,
        "sajda": false
      }
    ],
    "surahs": {
      "67": {
        "number": 67,
        "name": "سُورَةُ المُلۡكِ",
        "englishName": "Al-Mulk",
        "englishNameTranslation": "The Sovereignty",
        "revelationType": "Meccan",
        "numberOfAyahs": 30
      }
    },
    "edition": {
      "identifier": "ar.muyassar",
      "language": "ar",
      "name": "تفسير المیسر",
      "englishName": "King Fahad Quran Complex",
      "format": "text",
      "type": "tafsir",
      "direction": "rtl"
    }
  }
}