{
  "code": 200,
  "status": "OK",
  "data": {
    "number": 595,
    "ayahs": [
      {
        "number": 6044,
        "text": "أقسم الله بالشمس ونهارها وإشراقها ضحى، وبالقمر إذا تبعها في الطلوع والأفول، وبالنهار إذا جلَّى الظلمة وكشفها، وبالليل عندما يغطي الأرض فيكون ما عليها مظلمًا، وبالسماء وبنائها المحكم، وبالأرض وبَسْطها، وبكل نفس وإكمال الله خلقها لأداء مهمتها، فبيَّن لها طريق الشر وطريق الخير، قد فاز مَن طهَّرها ونمَّاها بالخير، وقد خسر مَن أخفى نفسه في المعاصي.",
        "surah": {
          "number": 91,
          "name": "سُورَةُ الشَّمۡسِ",
          "englishName": "Ash-Shams",
          "englishNameTranslation": "The Sun",
          "revelationType": "Meccan",
          "numberOfAyahs": 15
        },
        "numberInSurah": 1,
        "juz": 30,
        "manzil": 7,
        "page": 595,
        "ruku": 533,
        "hizbQuarter": 238,
        "sajda": false
      },
      {
        "number": 6045,
        "text": "أقسم الله بالشمس ونهارها وإشراقها ضحى، وبالقمر إذا تبعها في الطلوع والأفول، وبالنهار إذا جلَّى الظلمة وكشفها، وبالليل عندما يغطي الأرض فيكون ما عليها مظلمًا، وبالسماء وبنائها المحكم، وبالأرض وبَسْطها، وبكل نفس وإكمال الله خلقها لأداء مهمتها، فبيَّن لها طريق الشر وطريق الخير، قد فاز مَن طهَّرها ونمَّاها بالخير، وقد خسر مَن أخفى نفسه في المعاصي.",
        "surah": {
          "number": 91,
          "name": "سُورَةُ الشَّمۡسِ",
          "englishName": "Ash-Shams",
          "englishNameTranslation": "The Sun",
          "revelationType": "Meccan",
          "numberOfAyahs": 15
        },
        "numberInSurah": 2,
        "juz": 30,
        "manzil": 7,
        "page": 595,
        "ruku": 533,
        "hizbQuarter": 238,
        "sajda": false
      },
      {
        "number": 6046,
        "text": "أقسم الله بالشمس ونهارها وإشراقها ضحى، وبالقمر إذا تبعها في الطلوع والأفول، وبالنهار إذا جلَّى الظلمة وكشفها، وبالليل عندما يغطي الأرض فيكون ما عليها مظلمًا، وبالسماء وبنائها المحكم، وبالأرض وبَسْطها، وبكل نفس وإكمال الله خلقها لأداء مهمتها، فبيَّن لها طريق الشر وطريق الخير، قد فاز مَن طهَّرها ونمَّاها بالخير، وقد خسر مَن أخفى نفسه في المعاصي.",
        "surah": {
          "number": 91,
          "name": "سُورَةُ الشَّمۡسِ",
          "englishName": "Ash-Shams",
          "englishNameTranslation": "The Sun",
          "revelationType": "Meccan",
          "numberOfAyahs": 15
        },
        "numberInSurah": 3,
        "juz": 30,
        "manzil": 7,
        "page": 595,
        "ruku": 533,
        "hizbQuarter": 238,
        "sajda": false
      },
      {
        "number": 6047,
        "text": "أقسم الله بالشمس ونهارها وإشراقها ضحى، وبالقمر إذا تبعها في الطلوع والأفول، وبالنهار إذا جلَّى الظلمة وكشفها، وبالليل عندما يغطي الأرض فيكون ما عليها مظلمًا، وبالسماء وبنائها المحكم، وبالأرض وبَسْطها، وبكل نفس وإكمال الله خلقها لأداء مهمتها، فبيَّن لها طريق الشر وطريق الخير، قد فاز مَن طهَّرها ونمَّاها بالخير، وقد خسر مَن أخفى نفسه في المعاصي.",
        "surah": {
          "number": 91,
          "name": "سُورَةُ الشَّمۡسِ",
          "englishName": "Ash-Shams",
          "englishNameTranslation": "The Sun",
          "revelationType": "Meccan",
          "numberOfAyahs": 15
        },
        "numberInSurah": 4,
        "juz": 30,
        "manzil": 7,
        "page": 595,
        "ruku": 533,
        "hizbQuarter": 238,
        "sajda": false
      },
      {
        "number": 6048,
        "text": "أقسم الله بالشمس ونهارها وإشراقها ضحى، وبالقمر إذا تبعها في الطلوع والأفول، وبالنهار إذا جلَّى الظلمة وكشفها، وبالليل عندما يغطي الأرض فيكون ما عليها مظلمًا، وبالسماء وبنائها المحكم، وبالأرض وبَسْطها، وبكل نفس وإكمال الله خلقها لأداء مهمتها، فبيَّن لها طريق الشر وطريق الخير، قد فاز مَن طهَّرها ونمَّاها بالخير، وقد خسر مَن أخفى نفسه في المعاصي.",
        "surah": {
          "number": 91,
          "name": "سُورَةُ الشَّمۡسِ",
          "englishName": "Ash-Shams",
          "englishNameTranslation": "The Sun",
          "revelationType": "Meccan",
          "numberOfAyahs": 15
        },
        "numberInSurah": 5,
        "juz": 30,
        "manzil": 7,
        "page": 595,
        "ruku": 533,
        "hizbQuarter": 238,
        "sajda": false
      },
      {
        "number": 6049,
        "text": "أقسم الله بالشمس ونهارها وإشراقها ضحى، وبالقمر إذا تبعها في الطلوع والأفول، وبالنهار إذا جلَّى الظلمة وكشفها، وبالليل عندما يغطي الأرض فيكون ما عليها مظلمًا، وبالسماء وبنائها المحكم، وبالأرض وبَسْطها، وبكل نفس وإكمال الله خلقها لأداء مهمتها، فبيَّن لها طريق الشر وطريق الخير، قد فاز مَن طهَّرها ونمَّاها بالخير، وقد خسر مَن أخفى نفسه في المعاصي.",
        "surah": {
          "number": 91,
          "name": "سُورَةُ الشَّمۡسِ",
          "englishName": "Ash-Shams",
          "englishNameTranslation": "The Sun",
          "revelationType": "Meccan",
          "numberOfAyahs": 15
        },
        "numberInSurah": 6,
        "juz": 30,
        "manzil": 7,
        "page": 595,
        "ruku": 533,
        "hizbQuarter": 238,
        "sajda": false
      },
      {
        "number": 6050,
        "text": "أقسم الله بالشمس ونهارها وإشراقها ضحى، وبالقمر إذا تبعها في الطلوع والأفول، وبالنهار إذا جلَّى الظلمة وكشفها، وبالليل عندما يغطي الأرض فيكون ما عليها مظلمًا، وبالسماء وبنائها المحكم، وبالأرض وبَسْطها، وبكل نفس وإكمال الله خلقها لأداء مهمتها، فبيَّن لها طريق الشر وطريق الخير، قد فاز مَن طهَّرها ونمَّاها بالخير، وقد خسر مَن أخفى نفسه في المعاصي.",
        "surah": {
          "number": 91,
          "name": "سُورَةُ الشَّمۡسِ",
          "englishName": "Ash-Shams",
          "englishNameTranslation": "The Sun",
          "revelationType": "Meccan",
          "numberOfAyahs": 15
        },
        "numberInSurah": 7,
        "juz": 30,
        "manzil": 7,
        "page": 595,
        "ruku": 533,
        "hizbQuarter": 238,
        "sajda": false
      },
      {
        "number": 6051,
        "text": "أقسم الله بالشمس ونهارها وإشراقها ضحى، وبالقمر إذا تبعها في الطلوع والأفول، وبالنهار إذا جلَّى الظلمة وكشفها، وبالليل عندما يغطي الأرض فيكون ما عليها مظلمًا، وبالسماء وبنائها المحكم، وبالأرض وبَسْطها، وبكل نفس وإكمال الله خلقها لأداء مهمتها، فبيَّن لها طريق الشر وطريق الخير، قد فاز مَن طهَّرها ونمَّاها بالخير، وقد خسر مَن أخفى نفسه في المعاصي.",
        "surah": {
          "number": 91,
          "name": "سُورَةُ الشَّمۡسِ",
          "englishName": "Ash-Shams",
          "englishNameTranslation": "The Sun",
          "revelationType": "Meccan",
          "numberOfAyahs": 15
        },
        "numberInSurah": 8,
        "juz": 30,
        "manzil": 7,
        "page": 595,
        "ruku": 533,
        "hizbQuarter": 238,
        "sajda": false
      },
      {
        "number": 6052,
        "text": "أقسم الله بالشمس ونهارها وإشراقها ضحى، وبالقمر إذا تبعها في الطلوع والأفول، وبالنهار إذا جلَّى الظلمة وكشفها، وبالليل عندما يغطي الأرض فيكون ما عليها مظلمًا، وبالسماء وبنائها المحكم، وبالأرض وبَسْطها، وبكل نفس وإكمال الله خلقها لأداء مهمتها، فبيَّن لها طريق الشر وطريق الخير، قد فاز مَن طهَّرها ونمَّاها بالخير، وقد خسر مَن أخفى نفسه في المعاصي.",
        "surah": {
          "number": 91,
          "name": "سُورَةُ الشَّمۡسِ",
          "englishName": "Ash-Shams",
          "englishNameTranslation": "The Sun",
          "revelationType": "Meccan",
          "numberOfAyahs": 15
        },
        "numberInSurah": 9,
        "juz": 30,
        "manzil": 7,
        "page": 595,
        "ruku": 533,
        "hizbQuarter": 238,
        "sajda": false
      },
      {
        "number": 6053,
        "text": "أقسم الله بالشمس ونهارها وإشراقها ضحى، وبالقمر إذا تبعها في الطلوع والأفول، وبالنهار إذا جلَّى الظلمة وكشفها، وبالليل عندما يغطي الأرض فيكون ما عليها مظلمًا، وبالسماء وبنائها المحكم، وبالأرض وبَسْطها، وبكل نفس وإكمال الله خلقها لأداء مهمتها، فبيَّن لها طريق الشر وطريق الخير، قد فاز مَن طهَّرها ونمَّاها بالخير، وقد خسر مَن أخفى نفسه في المعاصي.",
        "surah": {
          "number": 91,
          "name": "سُورَةُ الشَّمۡسِ",
          "englishName": "Ash-Shams",
          "englishNameTranslation": "The Sun",
          "revelationType": "Meccan",
          "numberOfAyahs": 15
        },
        "numberInSurah": 10,
        "juz": 30,
        "manzil": 7,
        "page": 595,
        "ruku": 533,
        "hizbQuarter": 238,
        "sajda": false
      },
      {
        "number": 6054,
        "text": "كذَّبت ثمود نبيها ببلوغها الغاية في العصيان، إذ نهض أكثر القبيلة شقاوة لعقر الناقة، فقال لهم رسول الله صالح عليه السلام: احذروا أن تمسوا الناقة بسوء؛ فإنها آية أرسلها الله إليكم، تدل على صدق نبيكم، واحذروا أن تعتدوا على سقيها، فإن لها شِرْب يوم ولكم شِرْب يوم معلوم. فشق عليهم ذلك، فكذبوه فيما توعَّدهم به فنحروها، فأطبق عليهم ربهم العقوبة بجرمهم، فجعلها عليهم على السواء فلم يُفْلِت منهم أحد. ولا يخاف- جلت قدرته- تبعة ما أنزله بهم من شديد العقاب.",
        "surah": {
          "number": 91,
          "name": "سُورَةُ الشَّمۡسِ",
          "englishName": "Ash-Shams",
          "englishNameTranslation": "The Sun",
          "revelationType": "Meccan",
          "numberOfAyahs": 15
        },
        "numberInSurah": 11,
        "juz": 30,
        "manzil": 7,
        "page": 595,
        "ruku": 533,
        "hizbQuarter": 238,
        "sajda": false
      },
      {
        "number": 6055,
        "text": "كذَّبت ثمود نبيها ببلوغها الغاية في العصيان، إذ نهض أكثر القبيلة شقاوة لعقر الناقة، فقال لهم رسول الله صالح عليه السلام: احذروا أن تمسوا الناقة بسوء؛ فإنها آية أرسلها الله إليكم، تدل على صدق نبيكم، واحذروا أن تعتدوا على سقيها، فإن لها شِرْب يوم ولكم شِرْب يوم معلوم. فشق عليهم ذلك، فكذبوه فيما توعَّدهم به فنحروها، فأطبق عليهم ربهم العقوبة بجرمهم، فجعلها عليهم على السواء فلم يُفْلِت منهم أحد. ولا يخاف- جلت قدرته- تبعة ما أنزله بهم من شديد العقاب.",
        "surah": {
          "number": 91,
          "name": "سُورَةُ الشَّمۡسِ",
          "englishName": "Ash-Shams",
          "englishNameTranslation": "The Sun",
          "revelationType": "Meccan",
          "numberOfAyahs": 15
        },
        "numberInSurah": 12,
        "juz": 30,
        "manzil": 7,
        "page": 595,
        "ruku": 533,
        "hizbQuarter": 238,
        "sajda": false
      },
      {
        "number": 6056,
        "text": "كذَّبت ثمود نبيها ببلوغها الغاية في العصيان، إذ نهض أكثر القبيلة شقاوة لعقر الناقة، فقال لهم رسول الله صالح عليه السلام: احذروا أن تمسوا الناقة بسوء؛ فإنها آية أرسلها الله إليكم، تدل على صدق نبيكم، واحذروا أن تعتدوا على سقيها، فإن لها شِرْب يوم ولكم شِرْب يوم معلوم. فشق عليهم ذلك، فكذبوه فيما توعَّدهم به فنحروها، فأطبق عليهم ربهم العقوبة بجرمهم، فجعلها عليهم على السواء فلم يُفْلِت منهم أحد. ولا يخاف- جلت قدرته- تبعة ما أنزله بهم من شديد العقاب.",
        "surah": {
          "number": 91,
          "name": "سُورَةُ الشَّمۡسِ",
          "englishName": "Ash-Shams",
          "englishNameTranslation": "The Sun",
          "revelationType": "Meccan",
          "numberOfAyahs": 15
        },
        "numberInSurah": 13,
        "juz": 30,
        "manzil": 7,
        "page": 595,
        "ruku": 533,
        "hizbQuarter": 238,
        "sajda": false
      },
      {
        "number": 6057,
        "text": "كذَّبت ثمود نبيها ببلوغها الغاية في العصيان، إذ نهض أكثر القبيلة شقاوة لعقر الناقة، فقال لهم رسول الله صالح عليه السلام: احذروا أن تمسوا الناقة بسوء؛ فإنها آية أرسلها الله إليكم، تدل على صدق نبيكم، واحذروا أن تعتدوا على سقيها، فإن لها شِرْب يوم ولكم شِرْب يوم معلوم. فشق عليهم ذلك، فكذبوه فيما توعَّدهم به فنحروها، فأطبق عليهم ربهم العقوبة بجرمهم، فجعلها عليهم على السواء فلم يُفْلِت منهم أحد. ولا يخاف- جلت قدرته- تبعة ما أنزله بهم من شديد العقاب.",
        "surah": {
          "number": 91,
          "name": "سُورَةُ الشَّمۡسِ",
          "englishName": "Ash-Shams",
          "englishNameTranslation": "The Sun",
          "revelationType": "Meccan",
          "numberOfAyahs": 15
        },
        "numberInSurah": 14,
        "juz": 30,
        "manzil": 7,
        "page": 595,
        "ruku": 533,
        "hizbQuarter": 238,
        "sajda": false
      },
      {
        "number": 6058,
        "text": "كذَّبت ثمود نبيها ببلوغها الغاية في العصيان، إذ نهض أكثر القبيلة شقاوة لعقر الناقة، فقال لهم رسول الله صالح عليه السلام: احذروا أن تمسوا الناقة بسوء؛ فإنها آية أرسلها الله إليكم، تدل على صدق نبيكم، واحذروا أن تعتدوا على سقيها، فإن لها شِرْب يوم ولكم شِرْب يوم معلوم. فشق عليهم ذلك، فكذبوه فيما توعَّدهم به فنحروها، فأطبق عليهم ربهم العقوبة بجرمهم، فجعلها عليهم على السواء فلم يُفْلِت منهم أحد. ولا يخاف- جلت قدرته- تبعة ما أنزله بهم من شديد العقاب.",
        "surah": {
          "number": 91,
          "name": "سُورَةُ الشَّمۡسِ",
          "englishName": "Ash-Shams",
          "englishNameTranslation": "The Sun",
          "revelationType": "Meccan",
          "numberOfAyahs": 15
        },
        "numberInSurah": 15,
        "juz": 30,
        "manzil": 7,
        "page": 595,
        "ruku": 533,
        "hizbQuarter": 238,
        "sajda": false
      },
      {
        "number": 6059,
        "text": "أقسم الله سبحانه بالليل عندما يغطي بظلامه الأرض وما عليها، وبالنهار إذا انكشف عن ظلام الليل بضيائه، وبخلق الزوجين: الذكر والأنثى. إن عملكم لمختلف بين عامل للدنيا وعامل للآخرة.",
        "surah": {
          "number": 92,
          "name": "سُورَةُ اللَّيۡلِ",
          "englishName": "Al-Lail",
          "englishNameTranslation": "The Night",
          "revelationType": "Meccan",
          "numberOfAyahs": 21
        },
        "numberInSurah": 1,
        "juz": 30,
        "manzil": 7,
        "page": 595,
        "ruku": 534,
        "hizbQuarter": 238,
        "sajda": false
      },
      {
        "number": 6060,
        "text": "أقسم الله سبحانه بالليل عندما يغطي بظلامه الأرض وما عليها، وبالنهار إذا انكشف عن ظلام الليل بضيائه، وبخلق الزوجين: الذكر والأنثى. إن عملكم لمختلف بين عامل للدنيا وعامل للآخرة.",
        "surah": {
          "number": 92,
          "name": "سُورَةُ اللَّيۡلِ",
          "englishName": "Al-Lail",
          "englishNameTranslation": "The Night",
          "revelationType": "Meccan",
          "numberOfAyahs": 21
        },
        "numberInSurah": 2,
        "juz": 30,
        "manzil": 7,
        "page": 595,
        "ruku": 534,
        "hizbQuarter": 238,
        "sajda": false
      },
      {
        "number": 6061,
        "text": "أقسم الله سبحانه بالليل عندما يغطي بظلامه الأرض وما عليها، وبالنهار إذا انكشف عن ظلام الليل بضيائه، وبخلق الزوجين: الذكر والأنثى. إن عملكم لمختلف بين عامل للدنيا وعامل للآخرة.",
        "surah": {
          "number": 92,
          "name": "سُورَةُ اللَّيۡلِ",
          "englishName": "Al-Lail",
          "englishNameTranslation": "The Night",
          "revelationType": "Meccan",
          "numberOfAyahs": 21
        },
        "numberInSurah": 3,
        "juz": 30,
        "manzil": 7,
        "page": 595,
        "ruku": 534,
        "hizbQuarter": 238,
        "sajda": false
      },
      {
        "number": 6062,
        "text": "أقسم الله سبحانه بالليل عندما يغطي بظلامه الأرض وما عليها، وبالنهار إذا انكشف عن ظلام الليل بضيائه، وبخلق الزوجين: الذكر والأنثى. إن عملكم لمختلف بين عامل للدنيا وعامل للآخرة.",
        "surah": {
          "number": 92,
          "name": "سُورَةُ اللَّيۡلِ",
          "englishName": "Al-Lail",
          "englishNameTranslation": "The Night",
          "revelationType": "Meccan",
          "numberOfAyahs": 21
        },
        "numberInSurah": 4,
        "juz": 30,
        "manzil": 7,
        "page": 595,
        "ruku": 534,
        "hizbQuarter": 238,
        "sajda": false
      },
      {
        "number": 6063,
        "text": "فأمَّا من بذل من ماله واتقى الله في ذلك، وصدَّق بـ\"لا إله إلا الله\" وما دلت عليه، وما ترتب عليها من الجزاء، فسنرشده ونوفقه إلى أسباب الخير والصلاح ونيسِّر له أموره.",
        "surah": {
          "number": 92,
          "name": "سُورَةُ اللَّيۡلِ",
          "englishName": "Al-Lail",
          "englishNameTranslation": "The Night",
          "revelationType": "Meccan",
          "numberOfAyahs": 21
        },
        "numberInSurah": 5,
        "juz": 30,
        "manzil": 7,
        "page": 595,
        "ruku": 534,
        "hizbQuarter": 238,
        "sajda": false
      },
      {
        "number": 6064,
        "text": "فأمَّا من بذل من ماله واتقى الله في ذلك، وصدَّق بـ\"لا إله إلا الله\" وما دلت عليه، وما ترتب عليها من الجزاء، فسنرشده ونوفقه إلى أسباب الخير والصلاح ونيسِّر له أموره.",
        "surah": {
          "number": 92,
          "name": "سُورَةُ اللَّيۡلِ",
          "englishName": "Al-Lail",
          "englishNameTranslation": "The Night",
          "revelationType": "Meccan",
          "numberOfAyahs": 21
        },
        "numberInSurah": 6,
        "juz": 30,
        "manzil": 7,
        "page": 595,
        "ruku": 534,
        "hizbQuarter": 238,
        "sajda": false
      },
      {
        "number": 6065,
        "text": "فأمَّا من بذل من ماله واتقى الله في ذلك، وصدَّق بـ\"لا إله إلا الله\" وما دلت عليه، وما ترتب عليها من الجزاء، فسنرشده ونوفقه إلى أسباب الخير والصلاح ونيسِّر له أموره.",
        "surah": {
          "number": 92,
          "name": "سُورَةُ اللَّيۡلِ",
          "englishName": "Al-Lail",
          "englishNameTranslation": "The Night",
          "revelationType": "Meccan",
          "numberOfAyahs": 21
        },
        "numberInSurah": 7,
        "juz": 30,
        "manzil": 7,
        "page": 595,
        "ruku": 534,
        "hizbQuarter": 238,
        "sajda": false
      },
      {
        "number": 6066,
        "text": "وأما مَن بخل بماله واستغنى عن جزاء ربه، وكذَّب بـ\"لا إله إلا الله\" وما دلت عليه، وما ترتب عليها من الجزاء، فسنُيَسِّر له أسباب الشقاء، ولا ينفعه ماله الذي بخل به إذا وقع في النار.",
        "surah": {
          "number": 92,
          "name": "سُورَةُ اللَّيۡلِ",
          "englishName": "Al-Lail",
          "englishNameTranslation": "The Night",
          "revelationType": "Meccan",
          "numberOfAyahs": 21
        },
        "numberInSurah": 8,
        "juz": 30,
        "manzil": 7,
        "page": 595,
        "ruku": 534,
        "hizbQuarter": 238,
        "sajda": false
      },
      {
        "number": 6067,
        "text": "وأما مَن بخل بماله واستغنى عن جزاء ربه، وكذَّب بـ\"لا إله إلا الله\" وما دلت عليه، وما ترتب عليها من الجزاء، فسنُيَسِّر له أسباب الشقاء، ولا ينفعه ماله الذي بخل به إذا وقع في النار.",
        "surah": {
          "number": 92,
          "name": "سُورَةُ اللَّيۡلِ",
          "englishName": "Al-Lail",
          "englishNameTranslation": "The Night",
          "revelationType": "Meccan",
          "numberOfAyahs": 21
        },
        "numberInSurah": 9,
        "juz": 30,
        "manzil": 7,
        "page": 595,
        "ruku": 534,
        "hizbQuarter": 238,
        "sajda": false
      },
      {
        "number": 6068,
        "text": "وأما مَن بخل بماله واستغنى عن جزاء ربه، وكذَّب بـ\"لا إله إلا الله\" وما دلت عليه، وما ترتب عليها من الجزاء، فسنُيَسِّر له أسباب الشقاء، ولا ينفعه ماله الذي بخل به إذا وقع في النار.",
        "surah": {
          "number": 92,
          "name": "سُورَةُ اللَّيۡلِ",
          "englishName": "Al-Lail",
          "englishNameTranslation": "The Night",
          "revelationType": "Meccan",
          "numberOfAyahs": 21
        },
        "numberInSurah": 10,
        "juz": 30,
        "manzil": 7,
        "page": 595,
        "ruku": 534,
        "hizbQuarter": 238,
        "sajda": false
      },
      {
        "number": 6069,
        "text": "وأما مَن بخل بماله واستغنى عن جزاء ربه، وكذَّب بـ\"لا إله إلا الله\" وما دلت عليه، وما ترتب عليها من الجزاء، فسنُيَسِّر له أسباب الشقاء، ولا ينفعه ماله الذي بخل به إذا وقع في النار.",
        "surah": {
          "number": 92,
          "name": "سُورَةُ اللَّيۡلِ",
          "englishName": "Al-Lail",
          "englishNameTranslation": "The Night",
          "revelationType": "Meccan",
          "numberOfAyahs": 21
        },
        "numberInSurah": 11,
        "juz": 30,
        "manzil": 7,
        "page": 595,
        "ruku": 534,
        "hizbQuarter": 238,
        "sajda": false
      },
      {
        "number": 6070,
        "text": "إن علينا بفضلنا وحكمتنا أن نبيِّن طريق الهدى الموصل إلى الله وجنته من طريق الضلال، وإن لنا ملك الحياة الآخرة والحياة الدنيا.",
        "surah": {
          "number": 92,
          "name": "سُورَةُ اللَّيۡلِ",
          "englishName": "Al-Lail",
          "englishNameTranslation": "The Night",
          "revelationType": "Meccan",
          "numberOfAyahs": 21
        },
        "numberInSurah": 12,
        "juz": 30,
        "manzil": 7,
        "page": 595,
        "ruku": 534,
        "hizbQuarter": 238,
        "sajda": false
      },
      {
        "number": 6071,
        "text": "إن علينا بفضلنا وحكمتنا أن نبيِّن طريق الهدى الموصل إلى الله وجنته من طريق الضلال، وإن لنا ملك الحياة الآخرة والحياة الدنيا.",
        "surah": {
          "number": 92,
          "name": "سُورَةُ اللَّيۡلِ",
          "englishName": "Al-Lail",
          "englishNameTranslation": "The Night",
          "revelationType": "Meccan",
          "numberOfAyahs": 21
        },
        "numberInSurah": 13,
        "juz": 30,
        "manzil": 7,
        "page": 595,
        "ruku": 534,
        "hizbQuarter": 238,
        "sajda": false
      },
      {
        "number": 6072,
        "text": "فحذَّرتكم- أيها الناس- وخوَّفتكم نارًا تتوهج، وهي نار جهنم.",
        "surah": {
          "number": 92,
          "name": "سُورَةُ اللَّيۡلِ",
          "englishName": "Al-Lail",
          "englishNameTranslation": "The Night",
          "revelationType": "Meccan",
          "numberOfAyahs": 21
        },
        "numberInSurah": 14,
        "juz": 30,
        "manzil": 7,
        "page": 595,
        "ruku": 534,
        "hizbQuarter": 238,
        "sajda": false
      }
    ],
    "surahs": {
      "91": {
        "number": 91,
        "name": "سُورَةُ الشَّمۡسِ",
        "englishName": "Ash-Shams",
        "englishNameTranslation": "The Sun",
        "revelationType": "Meccan",
        "numberOfAyahs": 15
      },
      "92": {
        "number": 92,
        "name": "سُورَةُ اللَّيۡلِ",
        "englishName": "Al-Lail",
        "englishNameTranslation": "The Night",
        "revelationType": "Meccan",
        "numberOfAyahs": 21
      }
    },
    "edition": {
      "identifier": "ar.muyassar",
      "language": "ar",
      "name": "تفسير المیسر",
      "englishName": "King Fahad Quran Complex",
      "format": "text",
      "type": "tafsir",
      "direction": "rtl"
    }
  }
}