{
  "code": 200,
  "status": "OK",
  "data": {
    "number": 433,
    "ayahs": [
      {
        "number": 3646,
        "text": "The day He will gather all of them together, He will ask the angels: \"Did they worship you?\"",
        "surah": {
          "number": 34,
          "name": "سُورَةُ سَبَإٍ",
          "englishName": "Saba",
          "englishNameTranslation": "Sheba",
          "revelationType": "Meccan",
          "numberOfAyahs": 54
        },
        "numberInSurah": 40,
        "juz": 22,
        "manzil": 5,
        "page": 433,
        "ruku": 374,
        "hizbQuarter": 173,
        "sajda": false
      },
      {
        "number": 3647,
        "text": "\"God forbid!\" (they will answer). \"You are our protector not they. In fact, they worshipped the devils. Most of them believed in them.\"",
        "surah": {
          "number": 34,
          "name": "سُورَةُ سَبَإٍ",
          "englishName": "Saba",
          "englishNameTranslation": "Sheba",
          "revelationType": "Meccan",
          "numberOfAyahs": 54
        },
        "numberInSurah": 41,
        "juz": 22,
        "manzil": 5,
        "page": 433,
        "ruku": 374,
        "hizbQuarter": 173,
        "sajda": false
      },
      {
        "number": 3648,
        "text": "That day you will have no power to profit or harm each other; and We shall say to the sinners: \"Taste the punishment of Fire which you had denied.\"",
        "surah": {
          "number": 34,
          "name": "سُورَةُ سَبَإٍ",
          "englishName": "Saba",
          "englishNameTranslation": "Sheba",
          "revelationType": "Meccan",
          "numberOfAyahs": 54
        },
        "numberInSurah": 42,
        "juz": 22,
        "manzil": 5,
        "page": 433,
        "ruku": 374,
        "hizbQuarter": 173,
        "sajda": false
      },
      {
        "number": 3649,
        "text": "When Our clear revelations are read out to them, they say: \"This is only a man who wants to turn you away from what your fathers used to worship.\" And they say: \"This is nothing but a fabricated lie.\" And those who do not believe say of the truth when it has reached them: \"This is nothing but pure sorcery.\"",
        "surah": {
          "number": 34,
          "name": "سُورَةُ سَبَإٍ",
          "englishName": "Saba",
          "englishNameTranslation": "Sheba",
          "revelationType": "Meccan",
          "numberOfAyahs": 54
        },
        "numberInSurah": 43,
        "juz": 22,
        "manzil": 5,
        "page": 433,
        "ruku": 374,
        "hizbQuarter": 173,
        "sajda": false
      },
      {
        "number": 3650,
        "text": "We did not give them any scripture to study, nor sent any warner before you.",
        "surah": {
          "number": 34,
          "name": "سُورَةُ سَبَإٍ",
          "englishName": "Saba",
          "englishNameTranslation": "Sheba",
          "revelationType": "Meccan",
          "numberOfAyahs": 54
        },
        "numberInSurah": 44,
        "juz": 22,
        "manzil": 5,
        "page": 433,
        "ruku": 374,
        "hizbQuarter": 173,
        "sajda": false
      },
      {
        "number": 3651,
        "text": "Those before them had also denied, and they could not reach a tenth of (the possibilities) We had given them, and still they called My apostles liars. How great was the change that I wrought in their condition then!",
        "surah": {
          "number": 34,
          "name": "سُورَةُ سَبَإٍ",
          "englishName": "Saba",
          "englishNameTranslation": "Sheba",
          "revelationType": "Meccan",
          "numberOfAyahs": 54
        },
        "numberInSurah": 45,
        "juz": 22,
        "manzil": 5,
        "page": 433,
        "ruku": 374,
        "hizbQuarter": 173,
        "sajda": false
      },
      {
        "number": 3652,
        "text": "Say: \"I urge upon you only one thing: Stand up for God two by two or one by one, and think and reflect!\" There is no madness about your companion. He is a warner against the dreadful affliction (that awaits).",
        "surah": {
          "number": 34,
          "name": "سُورَةُ سَبَإٍ",
          "englishName": "Saba",
          "englishNameTranslation": "Sheba",
          "revelationType": "Meccan",
          "numberOfAyahs": 54
        },
        "numberInSurah": 46,
        "juz": 22,
        "manzil": 5,
        "page": 433,
        "ruku": 375,
        "hizbQuarter": 174,
        "sajda": false
      },
      {
        "number": 3653,
        "text": "Say: \"The reward I ask is for yourself. My reward is due from none but God; and He is witness over everything.\"",
        "surah": {
          "number": 34,
          "name": "سُورَةُ سَبَإٍ",
          "englishName": "Saba",
          "englishNameTranslation": "Sheba",
          "revelationType": "Meccan",
          "numberOfAyahs": 54
        },
        "numberInSurah": 47,
        "juz": 22,
        "manzil": 5,
        "page": 433,
        "ruku": 375,
        "hizbQuarter": 174,
        "sajda": false
      },
      {
        "number": 3654,
        "text": "Say: \"My Lord casts the truth: He is the knower of things unknown.\"",
        "surah": {
          "number": 34,
          "name": "سُورَةُ سَبَإٍ",
          "englishName": "Saba",
          "englishNameTranslation": "Sheba",
          "revelationType": "Meccan",
          "numberOfAyahs": 54
        },
        "numberInSurah": 48,
        "juz": 22,
        "manzil": 5,
        "page": 433,
        "ruku": 375,
        "hizbQuarter": 174,
        "sajda": false
      }
    ],
    "surahs": {
      "34": {
        "number": 34,
        "name": "سُورَةُ سَبَإٍ",
        "englishName": "Saba",
        "englishNameTranslation": "Sheba",
        "revelationType": "Meccan",
        "numberOfAyahs": 54
      }
    },
    "edition": {
      "identifier": "en.ahmedali",
      "language": "en",
      "name": "Ahmed Ali",
      "englishName": "Ahmed Ali",
      "format": "text",
      "type": "translation",
      "direction": "ltr"
    }
  }
}